yeonjae_universal_notification_service/__init__.py
yeonjae_universal_notification_service/exceptions.py
yeonjae_universal_notification_service/models.py
yeonjae_universal_notification_service/py.typed
yeonjae_universal_notification_service/service.py
yeonjae_universal_notification_service-1.0.5.dist-info/METADATA
yeonjae_universal_notification_service-1.0.5.dist-info/WHEEL
yeonjae_universal_notification_service-1.0.5.dist-info/top_level.txt
yeonjae_universal_notification_service-1.0.5.dist-info/RECORD
