Metadata-Version: 2.4
Name: yeonjae-universal-notification-service
Version: 1.0.5
Summary: Universal notification service supporting Slack, Email, Discord, and webhooks for automated reporting
Author-email: "CodePing.AI Team" <contact@codeping.ai>
License: MIT
Project-URL: Homepage, https://github.com/yeonjae-work/universal-modules
Project-URL: Repository, https://github.com/yeonjae-work/universal-modules
Project-URL: Issues, https://github.com/yeonjae-work/universal-modules/issues
Project-URL: Changelog, https://github.com/yeonjae-work/universal-modules/blob/main/packages/yeonjae-universal-notification-service/CHANGELOG.md
Keywords: notification,slack,email,discord,webhook,alerts,messaging,automation
Classifier: Development Status :: 5 - Production/Stable
Classifier: Intended Audience :: Developers
Classifier: License :: OSI Approved :: MIT License
Classifier: Operating System :: OS Independent
Classifier: Programming Language :: Python :: 3
Classifier: Programming Language :: Python :: 3.8
Classifier: Programming Language :: Python :: 3.9
Classifier: Programming Language :: Python :: 3.10
Classifier: Programming Language :: Python :: 3.11
Classifier: Programming Language :: Python :: 3.12
Classifier: Topic :: Software Development :: Libraries :: Python Modules
Classifier: Topic :: Communications :: Email
Classifier: Topic :: Communications :: Chat
Classifier: Topic :: System :: Monitoring
Requires-Python: >=3.8
Requires-Dist: typing-extensions>=4.0.0; python_version < "3.10"
Requires-Dist: requests>=2.28.0
Provides-Extra: slack
Requires-Dist: slack-sdk>=3.20.0; extra == "slack"
Provides-Extra: email
Requires-Dist: aiosmtplib>=2.0.0; extra == "email"
Requires-Dist: email-validator>=2.0.0; extra == "email"
Provides-Extra: discord
Requires-Dist: discord.py>=2.0.0; extra == "discord"
Provides-Extra: all
Requires-Dist: slack-sdk>=3.20.0; extra == "all"
Requires-Dist: aiosmtplib>=2.0.0; extra == "all"
Requires-Dist: email-validator>=2.0.0; extra == "all"
Requires-Dist: discord.py>=2.0.0; extra == "all"
Provides-Extra: dev
Requires-Dist: pytest>=7.0.0; extra == "dev"
Requires-Dist: pytest-asyncio>=0.21.0; extra == "dev"
Requires-Dist: pytest-mock>=3.10.0; extra == "dev"
Requires-Dist: black>=23.0.0; extra == "dev"
Requires-Dist: isort>=5.12.0; extra == "dev"
Requires-Dist: flake8>=6.0.0; extra == "dev"
Requires-Dist: mypy>=1.0.0; extra == "dev"
Requires-Dist: responses>=0.23.0; extra == "dev"
